HAllA-0.8.40-py3.7.egg-info/PKG-INFO
HAllA-0.8.40-py3.7.egg-info/SOURCES.txt
HAllA-0.8.40-py3.7.egg-info/dependency_links.txt
HAllA-0.8.40-py3.7.egg-info/entry_points.txt
HAllA-0.8.40-py3.7.egg-info/requires.txt
HAllA-0.8.40-py3.7.egg-info/top_level.txt
halla/__init__.py
halla/config.yaml
halla/config_loader.py
halla/hierarchy.py
halla/logger.py
halla/main.py
halla/utils/__init__.py
halla/utils/data.py
halla/utils/filesystem.py
halla/utils/report.py
halla/utils/similarity.py
halla/utils/stats.py
halla/utils/tree.py
scripts/__init__.py
scripts/diagnostic_plot.py
scripts/halla.py
scripts/hallagram.py
scripts/loader.py
scripts/synthetic_data.py
HAllA-0.8.40.dist-info/LICENSE
HAllA-0.8.40.dist-info/METADATA
HAllA-0.8.40.dist-info/WHEEL
HAllA-0.8.40.dist-info/entry_points.txt
HAllA-0.8.40.dist-info/top_level.txt
HAllA-0.8.40.dist-info/RECORD
